{"stat.walkOneCm":308677,"stat.useItem.minecraft.torch":15,"stat.leaveGame":12,"stat.mineBlock.minecraft.cobblestone":1,"stat.killEntity.Creeper":1,"stat.useItem.minecraft.diamond_sword":22,"stat.mineBlock.minecraft.sandstone":1,"stat.jump":1013,"stat.swimOneCm":8729,"stat.crouchOneCm":1935,"stat.sprintOneCm":130722,"achievement.exploreAllBiomes":{"value":0,"progress":["Savanna Plateau","ForestHills","DesertHills","Forest","River","Plains","Desert","Savanna"]},"achievement.openInventory":28,"stat.mineBlock.minecraft.leaves2":1,"stat.damageTaken":783,"stat.killEntity.Spider":5,"stat.useItem.minecraft.diamond_pickaxe":378,"stat.killEntity.Enderman":1,"stat.mobKills":8,"stat.flyOneCm":271349,"stat.useItem.minecraft.ender_pearl":3,"stat.mineBlock.minecraft.sand":1,"stat.playOneMinute":115148,"stat.killEntity.Sheep":1,"stat.useItem.minecraft.cooked_beef":11,"stat.damageDealt":2216,"stat.timeSinceDeath":115148,"stat.mineBlock.minecraft.dirt":6,"stat.mineBlock.minecraft.stone":369,"stat.mineBlock.minecraft.tallgrass":8,"stat.diveOneCm":5200}