{"stat.crouchOneCm":1616,"achievement.exploreAllBiomes":{"value":0,"progress":["Forest","Desert","Savanna"]},"stat.craftingTableInteraction":4,"achievement.openInventory":13,"stat.useItem.minecraft.planks":12,"stat.climbOneCm":1090,"stat.craftItem.minecraft.ladder":3,"stat.useItem.minecraft.ladder":1,"stat.flyOneCm":1790,"achievement.buildWorkBench":2,"stat.timeSinceDeath":15369,"stat.leaveGame":6,"stat.mineBlock.minecraft.planks":2,"achievement.mineWood":6,"stat.useItem.minecraft.crafting_table":1,"stat.mineBlock.minecraft.leaves2":1,"stat.craftItem.minecraft.stick":8,"stat.playOneMinute":15369,"stat.mineBlock.minecraft.log2":6,"stat.jump":25,"stat.craftItem.minecraft.crafting_table":1,"stat.mineBlock.minecraft.tallgrass":5,"stat.walkOneCm":17158,"stat.craftItem.minecraft.planks":24,"stat.craftItem.minecraft.trapdoor":2,"stat.useItem.minecraft.trapdoor":1,"stat.sprintOneCm":4671}